AUTHORS.rst
HISTORY.rst
LICENSE.rst
MANIFEST.in
README.rst
requirements-dev.txt
requirements.txt
setup.py
celery_redis_sentinel/__init__.py
celery_redis_sentinel/backend.py
celery_redis_sentinel/redis_sentinel.py
celery_redis_sentinel/register.py
celery_redis_sentinel/task.py
celery_redis_sentinel/transport.py
celery_redis_sentinel.egg-info/PKG-INFO
celery_redis_sentinel.egg-info/SOURCES.txt
celery_redis_sentinel.egg-info/dependency_links.txt
celery_redis_sentinel.egg-info/requires.txt
celery_redis_sentinel.egg-info/top_level.txt
docs/Makefile
docs/conf.py
docs/index.rst
docs/api/celery_redis_sentinel.backend.rst
docs/api/celery_redis_sentinel.redis_sentinel.rst
docs/api/celery_redis_sentinel.register.rst
docs/api/celery_redis_sentinel.rst
docs/api/celery_redis_sentinel.task.rst
docs/api/celery_redis_sentinel.transport.rst
docs/api/modules.rst
tests/__init__.py
tests/test_backend.py
tests/test_redis_sentinel.py
tests/test_register.py
tests/test_task.py
tests/test_transport.py