Metadata-Version: 1.1
Name: celery-redis-sentinel
Version: 0.2.0
Summary: Celery broker and results backend implementation for Redis Sentinel
Home-page: https://github.com/dealertrack/celery-redis-sentinel
Author: Miroslav Shubernetskiy
Author-email: UNKNOWN
License: MIT
Keywords: celery redis sentinel broker results
Platform: UNKNOWN
Classifier: Intended Audience :: Developers
Classifier: Natural Language :: English
Classifier: License :: OSI Approved :: MIT License
Classifier: Programming Language :: Python
Classifier: Programming Language :: Python :: 2
Classifier: Programming Language :: Python :: 2.7
Classifier: Programming Language :: Python :: 3
Classifier: Programming Language :: Python :: 3.4
Classifier: Programming Language :: Python :: 3.5
Classifier: Development Status :: 2 - Pre-Alpha
